dynamoq/__init__.py
dynamoq-0.0.5.data/scripts/dynamoq
dynamoq-0.0.5.dist-info/DESCRIPTION.rst
dynamoq-0.0.5.dist-info/METADATA
dynamoq-0.0.5.dist-info/RECORD
dynamoq-0.0.5.dist-info/WHEEL
dynamoq-0.0.5.dist-info/metadata.json
dynamoq-0.0.5.dist-info/top_level.txt
